pyazblob/__init__.py
pyazblob/errors.py
pyazblob/logs.py
pyazblob/main.py
pyazblob/settings.py
pyazblob/commands/__init__.py
pyazblob/commands/upload.py
pyazblob-0.0.6.dist-info/LICENSE
pyazblob-0.0.6.dist-info/METADATA
pyazblob-0.0.6.dist-info/WHEEL
pyazblob-0.0.6.dist-info/entry_points.txt
pyazblob-0.0.6.dist-info/top_level.txt
pyazblob-0.0.6.dist-info/RECORD
