Metadata-Version: 2.1
Name: pyazblob
Version: 0.0.6
Summary: Python tool to upload files into Azure Storage Blob service from local file system
Home-page: https://github.com/RobertoPrevato/PyAzBlob
Author: RobertoPrevato
Author-email: roberto.prevato@gmail.com
License: MIT
Keywords: azure storage python bulk upload blob service
Classifier: Development Status :: 5 - Production/Stable
Classifier: License :: OSI Approved :: MIT License
Classifier: Programming Language :: Python :: 3
Classifier: Operating System :: OS Independent
License-File: LICENSE
Requires-Dist: click (==8.1.3)
Requires-Dist: essentials (~=1.1.5)
Requires-Dist: azure-storage-blob (==12.13.1)
Requires-Dist: azure-common (==1.1.28)
Requires-Dist: azure-core (==1.25.0)
